m_rs/MRs.py
m_rs/__init__.py
metamorphic_relations/Data.py
metamorphic_relations/ImageMR.py
metamorphic_relations/Info.py
metamorphic_relations/MR.py
metamorphic_relations/MRModel.py
metamorphic_relations/MRs.py
metamorphic_relations/Results.py
metamorphic_relations/Transform.py
metamorphic_relations/__init__.py
metamorphic_relations-0.1.2.dist-info/METADATA
metamorphic_relations-0.1.2.dist-info/WHEEL
metamorphic_relations-0.1.2.dist-info/top_level.txt
metamorphic_relations-0.1.2.dist-info/RECORD
